{
  "$schema": "https://json.schemastore.org/tsconfig",
  "display": "Medusa.js",
  "compilerOptions": {
    "target": "es2019",
    "allowJs": true,
    "esModuleInterop": true,
    "module": "commonjs",
    "moduleResolution": "node",
    "emitDecoratorMetadata": true,
    "experimentalDecorators": true,
    "skipLibCheck": true,
    "skipDefaultLibCheck": true,
    "declaration": true,
    "sourceMap": false,
    "forceConsistentCasingInFileNames": true,
    "resolveJsonModule": true,
    "checkJs": false,
    "jsx": "react-jsx"
  }
}
